LICENSE.md
MANIFEST.in
README.md
setup.py
ais_dom_frontend.egg-info/PKG-INFO
ais_dom_frontend.egg-info/SOURCES.txt
ais_dom_frontend.egg-info/dependency_links.txt
ais_dom_frontend.egg-info/not-zip-safe
ais_dom_frontend.egg-info/top_level.txt
hass_frontend/__init__.py
hass_frontend/authorize.html
hass_frontend/index.html
hass_frontend/onboarding.html
hass_frontend/robots.txt
hass_frontend/service_worker.js
hass_frontend/frontend_es5/3c481c237c92772bbc63.worker.js
hass_frontend/frontend_es5/3c481c237c92772bbc63.worker.js.gz
hass_frontend/frontend_es5/3c481c237c92772bbc63.worker.js.map
hass_frontend/frontend_es5/app.8c3bad97.js
hass_frontend/frontend_es5/app.8c3bad97.js.LICENSE
hass_frontend/frontend_es5/app.8c3bad97.js.gz
hass_frontend/frontend_es5/app.8c3bad97.js.map
hass_frontend/frontend_es5/authorize.3fc3d6a0.js
hass_frontend/frontend_es5/authorize.3fc3d6a0.js.LICENSE
hass_frontend/frontend_es5/authorize.3fc3d6a0.js.gz
hass_frontend/frontend_es5/authorize.3fc3d6a0.js.map
hass_frontend/frontend_es5/chunk.0082532d701f7ef19030.js
hass_frontend/frontend_es5/chunk.0082532d701f7ef19030.js.gz
hass_frontend/frontend_es5/chunk.0082532d701f7ef19030.js.map
hass_frontend/frontend_es5/chunk.00e157bbbbed71e56637.js
hass_frontend/frontend_es5/chunk.00e157bbbbed71e56637.js.LICENSE
hass_frontend/frontend_es5/chunk.00e157bbbbed71e56637.js.gz
hass_frontend/frontend_es5/chunk.00e157bbbbed71e56637.js.map
hass_frontend/frontend_es5/chunk.02af93a34089e114526d.js
hass_frontend/frontend_es5/chunk.02af93a34089e114526d.js.gz
hass_frontend/frontend_es5/chunk.02af93a34089e114526d.js.map
hass_frontend/frontend_es5/chunk.04278ece681d8a471dbf.js
hass_frontend/frontend_es5/chunk.04278ece681d8a471dbf.js.LICENSE
hass_frontend/frontend_es5/chunk.04278ece681d8a471dbf.js.gz
hass_frontend/frontend_es5/chunk.04278ece681d8a471dbf.js.map
hass_frontend/frontend_es5/chunk.0463b2395f4dd3a664f3.js
hass_frontend/frontend_es5/chunk.0463b2395f4dd3a664f3.js.gz
hass_frontend/frontend_es5/chunk.0463b2395f4dd3a664f3.js.map
hass_frontend/frontend_es5/chunk.04af8e3ec1322d08929c.js
hass_frontend/frontend_es5/chunk.04af8e3ec1322d08929c.js.gz
hass_frontend/frontend_es5/chunk.04af8e3ec1322d08929c.js.map
