Metadata-Version: 1.0
Name: ais-dom-frontend
Version: 20200427.6
Summary: AIS dom frontend
Home-page: https://github.com/sviete/home-assistant/home-assistant-polymer
Author: The Authors of the AI-Speaker.com project.
Author-email: info@sviete.pl
License: Apache License 2.0
Platform: UNKNOWN
